capistry/__init__.py
capistry/_math.py
capistry/cap.py
capistry/compare.py
capistry/ergogen.py
capistry/fillet.py
capistry/logger.py
capistry/panel.py
capistry/sprue.py
capistry/stem.py
capistry/surface.py
capistry/taper.py
capistry/utils.py
capistry-0.2.0.dist-info/METADATA
capistry-0.2.0.dist-info/WHEEL
capistry-0.2.0.dist-info/licenses/LICENSE.md
capistry-0.2.0.dist-info/RECORD
