Metadata-Version: 2.4
Name: capistry
Version: 0.2.0
Summary: A Python package for parametric 3D modeling of keyboard keycaps.
Project-URL: Homepage, https://github.com/larssont/capistry
Project-URL: Repository, https://github.com/larssont/capistry
Project-URL: Issues, https://github.com/larssont/capistry/issues
Author: Tommy Larsson
License-Expression: MPL-2.0
License-File: LICENSE.md
Keywords: 3d modeling,3d printing,cad,keycap
Classifier: Operating System :: OS Independent
Classifier: Programming Language :: Python :: 3
Classifier: Programming Language :: Python :: 3.13
Classifier: Topic :: Multimedia :: Graphics :: 3D Modeling
Classifier: Topic :: Software Development :: Libraries
Requires-Python: >=3.13
Requires-Dist: attrs<26,>=25.3.0
Requires-Dist: build123d<1,>=0.9.1
Requires-Dist: mashumaro<4,>=3.16
Requires-Dist: more-itertools<11,>=10.7.0
Requires-Dist: rich<15,>=14.0.0
Requires-Dist: tzdata>=2025.2
